skestimate/__init__.py
skestimate/fit_est.py
skestimate/test_skestimate.py
skestimate-0.0.3.dist-info/LICENSE
skestimate-0.0.3.dist-info/METADATA
skestimate-0.0.3.dist-info/WHEEL
skestimate-0.0.3.dist-info/top_level.txt
skestimate-0.0.3.dist-info/RECORD
