Metadata-Version: 2.1
Name: skestimate
Version: 0.0.3
Summary: fit estimate utility
Home-page: https://github.com/skhabiri/EstimatorPkg
Author: skhabiri
License: UNKNOWN
Platform: UNKNOWN
Classifier: Programming Language :: Python :: 3
Classifier: License :: OSI Approved :: MIT License
Classifier: Operating System :: OS Independent
Requires-Python: >=3.6
Requires-Dist: numpy
Requires-Dist: pandas
Requires-Dist: matplotlib
Requires-Dist: scikit-learn
